Workbook

Sheet Start Here
A1: TRILLIONAIRE ME — REQUIREMENTS REGISTER v2.0 (companion to Canonical Spec v2.0)
A3: Field | B3: Meaning
A4: Status | B4: Specification stage. NOTHING is implemented. Every 'Verification' cell = Not verified. No repository, database or app was inspected or built.
A5: Authority | B5: Canonical Spec v2.0 > this Register > v1.x files (history only). Origin tags: U = user's own words · B = user-approved brief · S = original source document (second-hand; 3 originals not attached) · P = later spec/audit rule · I = assistant inference (needs owner confirmation).
A6: Priority (R) | B6: R0 = must pass before the first REAL sensitive data entry or the first external/consequential action that the requirement touches (see 'Must pass before gate'). R1 = must pass before a dependable first release. R2 = later. Separate from v1 'Priority' (kept for history) and from audit severity.
A7: Gate | B7: One vocabulary only: G0 spec freeze · G1 safe shell+field catalog · G2 Android offline prototype · G3 rule-based planner (≈80% without AI) · G4 research/options · G5 Deen content verification · G6 AI/automation · G7 privacy/recovery/real-data · G8 pilot→PC→public decision.
A8: Scope tag | B8: FIRST-BUILD = first needed in G1–G3. FULL-SCOPE, LATER = needed in the full product at the stated later gate. NOTHING is dropped; deferral reasons are in 'Deferrals'.
A9: Intent link | B9: Domain-level default mapping to the Intent Register (INT-xx). To be refined row-by-row at G0; new rows (142+) are mapped individually.
A10: Tests | B10: 'Tests v2' replaces all v1 tests. Each has method, threshold, dataset, blocked-by. Human-review rows are gates, not engineering tests. All status = Not run.
A11: Merged rows | B11: TM-REQ-135 → 126, TM-REQ-141 → 120 (rows kept, marked MERGED, excluded from active counts).
A12: Estimates | B12: Counts on 'Summary' are formulas over 'Requirements v2'. Nothing here is a time/cost estimate.
A13: Sheets | B13: Summary · Requirements v2 · Tests v2 · Intent Register · Gates · Decisions · Deferrals · Conflicts · Visual Refs · Change Log

Sheet Summary
A1: SUMMARY — live counts (formulas over 'Requirements v2')
A2: Active = not merged. Change a row in 'Requirements v2' and these update.
A4: Total rows | B4: =COUNTA('Requirements v2'!A4:A175)
A5: Merged rows | B5: =COUNTIF('Requirements v2'!L4:L175,"MERGED*")
A6: Active rows | B6: =B4-B5
A8: By R-priority (all rows)
A9: R0 | B9: =COUNTIF('Requirements v2'!F4:F175,A9)
A10: R1 | B10: =COUNTIF('Requirements v2'!F4:F175,A10)
A11: R2 | B11: =COUNTIF('Requirements v2'!F4:F175,A11)
A13: By first-needed gate
A14: G0 | B14: =COUNTIF('Requirements v2'!G4:G175,A14)
A15: G1 | B15: =COUNTIF('Requirements v2'!G4:G175,A15)
A16: G2 | B16: =COUNTIF('Requirements v2'!G4:G175,A16)
A17: G3 | B17: =COUNTIF('Requirements v2'!G4:G175,A17)
A18: G4 | B18: =COUNTIF('Requirements v2'!G4:G175,A18)
A19: G5 | B19: =COUNTIF('Requirements v2'!G4:G175,A19)
A20: G6 | B20: =COUNTIF('Requirements v2'!G4:G175,A20)
A21: G7 | B21: =COUNTIF('Requirements v2'!G4:G175,A21)
A22: G8 | B22: =COUNTIF('Requirements v2'!G4:G175,A22)
A24: By must-pass gate
A25: G0 | B25: =COUNTIF('Requirements v2'!H4:H175,A25)
A26: G1 | B26: =COUNTIF('Requirements v2'!H4:H175,A26)
A27: G2 | B27: =COUNTIF('Requirements v2'!H4:H175,A27)
A28: G3 | B28: =COUNTIF('Requirements v2'!H4:H175,A28)
A29: G4 | B29: =COUNTIF('Requirements v2'!H4:H175,A29)
A30: G5 | B30: =COUNTIF('Requirements v2'!H4:H175,A30)
A31: G6 | B31: =COUNTIF('Requirements v2'!H4:H175,A31)
A32: G7 | B32: =COUNTIF('Requirements v2'!H4:H175,A32)
A33: G8 | B33: =COUNTIF('Requirements v2'!H4:H175,A33)
A35: By origin (rows containing tag)
A36: U | B36: =COUNTIF('Requirements v2'!D4:D175,"*"&A36&"*")
A37: B | B37: =COUNTIF('Requirements v2'!D4:D175,"*"&A37&"*")
A38: S | B38: =COUNTIF('Requirements v2'!D4:D175,"*"&A38&"*")
A39: P | B39: =COUNTIF('Requirements v2'!D4:D175,"*"&A39&"*")
A40: I | B40: =COUNTIF('Requirements v2'!D4:D175,"*"&A40&"*")
A42: Scope: FIRST-BUILD (G1–G3 start) | B42: =COUNTIF('Requirements v2'!I4:I175,"FIRST-BUILD*")
A43: Scope: FULL-SCOPE, LATER | B43: =COUNTIF('Requirements v2'!I4:I175,"FULL-SCOPE*")
A44: Implemented (verified) | B44: =COUNTIF('Requirements v2'!O4:O175,"Verified*")
A46: Note: origin counts overlap (a row can carry two tags). 'Implemented' = 0 by design at specification stage.

Sheet Requirements v2
A1: REQUIREMENTS v2 — 172 rows (170 active, 2 merged)
A2: Filter by Gate / R / Origin / Domain. 'Implementation verification' = Not verified for all rows.
A3: Req ID | B3: Domain | C3: Requirement | D3: Origin | E3: Intent link | F3: R (v2) | G3: First needed gate | H3: Must pass before gate | I3: Scope tag | J3: v1 priority | K3: v1 coverage status | L3: Merge / cross-link | M3: Blocked by decision | N3: Test ID | O3: Implementation verification
A4: TM-REQ-001 | B4: Governance & outcomes | C4: Define what “Trillionaire” means for each target | D4: P+B | E4: INT-27,INT-09 | F4: R0 | G4: G1 | H4: G3 | I4: FIRST-BUILD (G1-G3) | J4: P0 | K4: Decision required | N4: TM-TST-001 | O4: Not verified — no build
A5: TM-REQ-002 | B5: Governance & outcomes | C5: Keep multiple north-star outcomes separate | D5: P | E5: INT-27,INT-09 | F5: R0 | G5: G1 | H5: G3 | I5: FIRST-BUILD (G1-G3) | J5: P0 | K5: Partial—gap remains | N5: TM-TST-002 | O5: Not verified — no build
A6: TM-REQ-003 | B6: Governance & outcomes | C6: Respect the user's value hierarchy, including Deen/Akhirah | D6: U+B | E6: INT-27,INT-09 | F6: R1 | G6: G1 | H6: G3 | I6: FIRST-BUILD (G1-G3) | J6: P0 | K6: Documented—implementation unverified | N6: TM-TST-003 | O6: Verified for G1 scope (automated evidence) — see Tests v2
A7: TM-REQ-004 | B7: Governance & outcomes | C7: Do not guarantee extreme wealth, investment returns or success | D7: P | E7: INT-27,INT-09 | F7: R0 | G7: G1 | H7: G3 | I7: FIRST-BUILD (G1-G3) | J7: P0 | K7: Documented—implementation unverified | N7: TM-TST-004 | O7: Not verified — no build
A8: TM-REQ-005 | B8: Governance & outcomes | C8: Treat old starting cash as an unverified historical claim | D8: P | E8: INT-27,INT-09 | F8: R0 | G8: G0 | H8: G1 | I8: FIRST-BUILD (G1-G3) | J8: P0 | K8: Source conflict / stale-risk | N8: TM-TST-005 | O8: Not verified — no build
A9: TM-REQ-006 | B9: Governance & outcomes | C9: Separate facts, estimates, assumptions, inferences and external evidence | D9: P | E9: INT-27,INT-09 | F9: R0 | G9: G1 | H9: G1 | I9: FIRST-BUILD (G1-G3) | J9: P0 | K9: Documented—implementation unverified | N9: TM-TST-006 | O9: Verified for G1 scope (automated evidence) — see Tests v2
A10: TM-REQ-007 | B10: Governance & outcomes | C10: Maintain source freshness and history | D10: P | E10: INT-27,INT-09 | F10: R1 | G10: G4 | H10: G4 | I10: FULL-SCOPE, LATER (G4) | J10: P1 | K10: Partial—gap remains | N10: TM-TST-007 | O10: Not verified — no build
A11: TM-REQ-008 | B11: Governance & outcomes | C11: Preserve a decision log and plan versions | D11: P | E11: INT-27,INT-09 | F11: R1 | G11: G3 | H11: G3 | I11: FIRST-BUILD (G1-G3) | J11: P1 | K11: Documented—implementation unverified | N11: TM-TST-008 | O11: Not verified — no build
A12: TM-REQ-009 | B12: Governance & outcomes | C12: Support no-deadline, paused and retired goals | D12: P | E12: INT-27,INT-09 | F12: R1 | G12: G3 | H12: G3 | I12: FIRST-BUILD (G1-G3) | J12: P1 | K12: Partial—gap remains | N12: TM-TST-009 | O12: Not verified — no build
A13: TM-REQ-010 | B13: Starting-point profile | C13: Progressive guided intake, not one giant form | D13: S | E13: INT-04,INT-10 | F13: R1 | G13: G1 | H13: G1 | I13: FIRST-BUILD (G1-G3) | J13: P0 | K13: Documented—implementation unverified | N13: TM-TST-010 | O13: Partial — automated part passes; manual/human gate pending — see Tests v2
A14: TM-REQ-011 | B14: Starting-point profile | C14: Personal identity, locale and time settings | D14: S | E14: INT-04,INT-10 | F14: R1 | G14: G1 | H14: G2 | I14: FIRST-BUILD (G1-G3) | J14: P1 | K14: Partial—gap remains | N14: TM-TST-011 | O14: Not verified — no build
A15: TM-REQ-012 | B15: Starting-point profile | C15: Education, experience and credentials | D15: S | E15: INT-04,INT-10 | F15: R1 | G15: G1 | H15: G3 | I15: FIRST-BUILD (G1-G3) | J15: P1 | K15: Documented—implementation unverified | N15: TM-TST-012 | O15: Not verified — no build
... A44: TM-REQ-041 | B44: Goal & execution engine | C44: Scheduling and habit supports are optional and non-punitive | D44: P | E44: INT-17,INT-26 | F44: R1 | G44: G3 | H44: G3 | I44: FIRST-BUILD (G1-G3) | J44: P1 | K44: Partial—gap remains | N44: TM-TST-041 | O44: Not verified — no build
A45: TM-REQ-042 | B45: Goal & execution engine | C45: Calendar integration is opt-in and reversible | D45: P | E45: INT-17,INT-26 | F45: R1 | G45: G6 | H45: G6 | I45: FULL-SCOPE, LATER (G6) | J45: P1 | K45: Partial—gap remains | L45: see 126 | N45: TM-TST-042 | O45: Not verified — no build
A46: TM-REQ-043 | B46: Goal & execution engine | C46: Weekly/monthly/quarterly reviews and reflection | D46: P | E46: INT-17,INT-26 | F46: R1 | G46: G3 | H46: G3 | I46: FIRST-BUILD (G1-G3) | J46: P1 | K46: Documented—implementation unverified | N46: TM-TST-043 | O46: Not verified — no build
A47: TM-REQ-044 | B47: Goal & execution engine | C47: Journal/voice notes are optional and sensitive | D47: P | E47: INT-17,INT-26 | F47: R1 | G47: G1 | H47: G7 | I47: FIRST-BUILD (G1-G3) | J47: P1 | K47: Partial—gap remains | N47: TM-TST-044 | O47: Not verified — no build
A48: TM-REQ-045 | B48: Goal & execution engine | C48: Real-life event capture triggers impact analysis | D48: P | E48: INT-17,INT-26 | F48: R0 | G48: G3 | H48: G3 | I48: FIRST-BUILD (G1-G3) | J48: P0 | K48: Documented—implementation unverified | N48: TM-TST-045 | O48: Not verified — no build
A49: TM-REQ-046 | B49: Goal & execution engine | C49: Preserve historical plan and compare alternatives | D49: P | E49: INT-17,INT-26 | F49: R1 | G49: G3 | H49: G3 | I49: FIRST-BUILD (G1-G3) | J49: P1 | K49: Documented—implementation unverified | N49: TM-TST-046 | O49: Not verified — no build
A50: TM-REQ-047 | B50: Goal & execution engine | C50: Overload, crisis and interruption modes | D50: B | E50: INT-17,INT-26 | F50: R0 | G50: G3 | H50: G3 | I50: FIRST-BUILD (G1-G3) | J50: P0 | K50: Partial—gap remains | N50: TM-TST-047 | O50: Not verified — no build
A51: TM-REQ-048 | B51: Goal & execution engine | C51: Do not infer task completion from untrusted sources alone | D51: P | E51: INT-17,INT-26 | F51: R1 | G51: G6 | H51: G6 | I51: FULL-SCOPE, LATER (G6) | J51: P1 | K51: Partial—gap remains | N51: TM-TST-048 | O51: Not verified — no build
A52: TM-REQ-049 | B52: Opportunity research & markets | C52: Research local and global markets with source provenance | D52: P | E52: INT-18,INT-31 | F52: R1 | G52: G4 | H52: G4 | I52: FULL-SCOPE, LATER (G4) | J52: P1 | K52: Documented—implementation unverified | N52: TM-TST-049 | O52: Not verified — no build
A53: TM-REQ-050 | B53: Opportunity research & markets | C53: Score demand, willingness to pay, competition and feasibility | D53: P | E53: INT-18,INT-31 | F53: R1 | G53: G4 | H53: G4 | I53: FULL-SCOPE, LATER (G4) | J53: P1 | K53: Documented—implementation unverified | N53: TM-TST-050 | O53: Not verified — no build
A54: TM-REQ-051 | B54: Opportunity research & markets | C54: Validate ideas with low-cost tests before major investment | D54: P | E54: INT-18,INT-31 | F54: R1 | G54: G4 | H54: G4 | I54: FULL-SCOPE, LATER (G4) | J54: P0 | K54: Documented—implementation unverified | N54: TM-TST-051 | O54: Not verified — no build
A55: TM-REQ-052 | B55: Opportunity research & markets | C55: Show evidence for and against; use base rates where defensible | D55: P | E55: INT-18,INT-31 | F55: R1 | G55: G4 | H55: G4 | I55: FULL-SCOPE, LATER (G4) | J55: P1 | K55: Partial—gap remains | N55: TM-TST-052 | O55: Not verified — no build
A56: TM-REQ-053 | B56: Opportunity research & markets | C56: Compare 2–3 strong options and let user save/customize/replace | D56: U | E56: INT-18,INT-31 | F56: R1 | G56: G4 | H56: G4 | I56: FULL-SCOPE, LATER (G4) | J56: P0 | K56: Documented—implementation unverified | N56: TM-TST-053 | O56: Not verified — no build
A57: TM-REQ-054 | B57: Opportunity research & markets | C57: Track price/offer/availability freshness and selected-option version | D57: P | E57: INT-18,INT-31 | F57: R1 | G57: G4 | H57: G4 | I57: FULL-SCOPE, LATER (G4) | J57: P1 | K57: Partial—gap remains | N57: TM-TST-054 | O57: Not verified — no build
... A72: TM-REQ-069 | B72: Visual-first UX | C72: Bangla/English quality and local conventions | D72: S | E72: INT-16,INT-04,INT-34 | F72: R1 | G72: G1 | H72: G2 | I72: FIRST-BUILD (G1-G3) | J72: P1 | K72: Partial—gap remains | N72: TM-TST-069 | O72: Not verified — no build
A73: TM-REQ-070 | B73: Visual-first UX | C73: Android-first, small screen, low bandwidth and optional desktop | D73: B | E73: INT-16,INT-04,INT-34 | F73: R1 | G73: G1 | H73: G2 | I73: FIRST-BUILD (G1-G3) | J73: P1 | K73: Partial—gap remains | M73: D-A | N73: TM-TST-070 | O73: Not verified — no build
A74: TM-REQ-071 | B74: Visual-first UX | C74: Use reminders without intrusive or shaming patterns | D74: P | E74: INT-16,INT-04,INT-34 | F74: R1 | G74: G2 | H74: G2 | I74: FIRST-BUILD (G1-G3) | J74: P1 | K74: Partial—gap remains | M74: D-A | N74: TM-TST-071 | O74: Not verified — no build
A75: TM-REQ-072 | B75: AI & research | C75: Keep canonical user data in the application database | D75: P | E75: INT-22,INT-35 | F75: R0 | G75: G1 | H75: G6 | I75: FIRST-BUILD (G1-G3) | J75: P0 | K75: Documented—implementation unverified | L75: see 083 (cross-link) | M75: D-C | N75: TM-TST-072 | O75: Not verified — no build
A76: TM-REQ-073 | B76: AI & research | C76: Use structured outputs and validated tools, not free-form action parsing | D76: P | E76: INT-22,INT-35 | F76: R0 | G76: G6 | H76: G6 | I76: FULL-SCOPE, LATER (G6) | J76: P0 | K76: Documented—implementation unverified | M76: D-C | N76: TM-TST-073 | O76: Not verified — no build
A77: TM-REQ-074 | B77: AI & research | C77: Keep model vs code responsibilities explicit | D77: P | E77: INT-22,INT-35 | F77: R0 | G77: G3 | H77: G3 | I77: FIRST-BUILD (G1-G3) | J77: P0 | K77: Documented—implementation unverified | N77: TM-TST-074 | O77: Not verified — no build
A78: TM-REQ-075 | B78: AI & research | C78: Treat web pages, PDFs, images and connector output as untrusted input | D78: P | E78: INT-22,INT-35 | F78: R0 | G78: G6 | H78: G6 | I78: FULL-SCOPE, LATER (G6) | J78: P0 | K78: Partial—gap remains | M78: D-C | N78: TM-TST-075 | O78: Not verified — no build
A79: TM-REQ-076 | B79: AI & research | C79: Cite sources, dates, confidence, conflict and unknowns | D79: P | E79: INT-22,INT-35 | F79: R1 | G79: G4 | H79: G4 | I79: FULL-SCOPE, LATER (G4) | J79: P1 | K79: Partial—gap remains | N79: TM-TST-076 | O79: Not verified — no build
A80: TM-REQ-077 | B80: AI & research | C80: Feature-specific provider retention and deletion mapping | D80: P | E80: INT-22,INT-35 | F80: R0 | G80: G6 | H80: G6 | I80: FULL-SCOPE, LATER (G6) | J80: P0 | K80: External verification required | M80: D-C | N80: TM-TST-077 | O80: Not verified — no build
A81: TM-REQ-078 | B81: AI & research | C81: Never expose API key in Android/browser client | D81: P | E81: INT-22,INT-35 | F81: R0 | G81: G6 | H81: G6 | I81: FULL-SCOPE, LATER (G6) | J81: P0 | K81: Documented—implementation unverified | M81: D-C | N81: TM-TST-078 | O81: Not verified — no build
A82: TM-REQ-079 | B82: AI & research | C82: Cost, quota, rate limits and offline mode stop uncontrolled calls | D82: P | E82: INT-22,INT-35 | F82: R0 | G82: G6 | H82: G6 | I82: FULL-SCOPE, LATER (G6) | J82: P0 | K82: Partial—gap remains | M82: D-C | N82: TM-TST-079 | O82: Not verified — no build
A83: TM-REQ-080 | B83: AI & research | C83: Own versioned regression/evaluation suite | D83: P | E83: INT-22,INT-35 | F83: R1 | G83: G6 | H83: G6 | I83: FULL-SCOPE, LATER (G6) | J83: P0 | K83: Partial—gap remains | M83: D-C | N83: TM-TST-080 | O83: Not verified — no build
A84: TM-REQ-081 | B84: AI & research | C84: Do not claim continuous learning unless mechanism is real | D84: P | E84: INT-22,INT-35 | F84: R1 | G84: G6 | H84: G6 | I84: FULL-SCOPE, LATER (G6) | J84: P1 | K84: Source conflict / stale-risk | M84: D-C | N84: TM-TST-081 | O84: Not verified — no build
A85: TM-REQ-082 | B85: AI & research | C85: Use least privilege and purpose-limited tool scopes | D85: P | E85: INT-22,INT-35 | F85: R0 | G85: G6 | H85: G6 | I85: FULL-SCOPE, LATER (G6) | J85: P0 | K85: Partial—gap remains | M85: D-C | N85: TM-TST-082 | O85: Not verified — no build
A86: TM-REQ-083 | B86: AI & research | C86: Support multiple providers without locking core data to one model | D86: P | E86: INT-22,INT-35 | F86: R1 | G86: G6 | H86: G6 | I86: FULL-SCOPE, LATER (G6) | J86: P1 | K86: Partial—gap remains | L86: see 072 (cross-link) | M86: D-C | N86: TM-TST-083 | O86: Not verified — no build
A87: TM-REQ-084 | B87: Offline & resilience | C87: Useful core works offline from local data source | D87: B | E87: INT-15,INT-34 | F87: R0 | G87: G2 | H87: G2 | I87: FIRST-BUILD (G1-G3) | J87: P0 | K87: Documented—implementation unverified | M87: D-A | N87: TM-TST-084 | O87: Not verified — no build
A88: TM-REQ-085 | B88: Offline & resilience | C88: Offline operation queue uses stable IDs and idempotent replay | D88: B | E88: INT-15,INT-34 | F88: R0 | G88: G2 | H88: G2 | I88: FIRST-BUILD (G1-G3) | J88: P0 | K88: Partial—gap remains | M88: D-A | N88: TM-TST-085 | O88: Not verified — no build
A89: TM-REQ-086 | B89: Offline & resilience | C89: Sync conflicts have visible, safe resolution | D89: B | E89: INT-15,INT-34 | F89: R0 | G89: G2 | H89: G2 | I89: FIRST-BUILD (G1-G3) | J89: P0 | K89: Partial—gap remains | M89: D-A | N89: TM-TST-086 | O89: Not verified — no build
A90: TM-REQ-087 | B90: Offline & resilience | C90: Show freshness, queue, error and last-sync states | D90: B | E90: INT-15,INT-34 | F90: R1 | G90: G2 | H90: G2 | I90: FIRST-BUILD (G1-G3) | J90: P1 | K90: Partial—gap remains | M90: D-A | N90: TM-TST-087 | O90: Not verified — no build
A91: TM-REQ-088 | B91: Offline & resilience | C91: Backups are encrypted, versioned and actually restorable | D91: B | E91: INT-15,INT-34 | F91: R0 | G91: G2 | H91: G2 | I91: FIRST-BUILD (G1-G3) | J91: P0 | K91: Partial—gap remains | M91: D-A | N91: TM-TST-088 | O91: Not verified — no build
A92: TM-REQ-089 | B92: Offline & resilience | C92: Schema migration and rollback strategy | D92: P | E92: INT-15,INT-34 | F92: R1 | G92: G2 | H92: G2 | I92: FIRST-BUILD (G1-G3) | J92: P1 | K92: Partial—gap remains | M92: D-A | N92: TM-TST-089 | O92: Not verified — no build
A93: TM-REQ-090 | B93: Offline & resilience | C93: Device loss/account recovery and session revocation | D93: P | E93: INT-15,INT-34 | F93: R1 | G93: G2 | H93: G7 | I93: FIRST-BUILD (G1-G3) | J93: P1 | K93: Partial—gap remains | M93: D-A | N93: TM-TST-090 | O93: Not verified — no build
A94: TM-REQ-091 | B94: Offline & resilience | C94: Offline religious schedule and content show limitations honestly | D94: P | E94: INT-15,INT-34 | F94: R1 | G94: G5 | H94: G5 | I94: FULL-SCOPE, LATER (G5) | J94: P1 | K94: Partial—gap remains | L94: see 101,112 | M94: D-D | N94: TM-TST-091 | O94: Not verified — no build
A95: TM-REQ-092 | B95: Security, privacy & compliance | C95: Classify and minimize sensitive and third-party data | D95: P | E95: INT-22 | F95: R0 | G95: G1 | H95: G1 | I95: FIRST-BUILD (G1-G3) | J95: P0 | K95: Partial—gap remains | M95: D-B | N95: TM-TST-092 | O95: Verified for G1 scope (automated evidence) — see Tests v2
A96: TM-REQ-093 | B96: Security, privacy & compliance | C96: Explicit consent by purpose and integration | D96: P | E96: INT-22 | F96: R0 | G96: G1 | H96: G7 | I96: FIRST-BUILD (G1-G3) | J96: P0 | K96: Partial—gap remains | M96: D-B | N96: TM-TST-093 | O96: Not verified — no build
A97: TM-REQ-094 | B97: Security, privacy & compliance | C97: Access, correction, portability, deletion and withdrawal workflows | D97: P | E97: INT-22 | F97: R0 | G97: G2 | H97: G7 | I97: FIRST-BUILD (G1-G3) | J97: P0 | K97: Partial—gap remains | M97: D-B | N97: TM-TST-094 | O97: Not verified — no build
A98: TM-REQ-095 | B98: Security, privacy & compliance | C98: Bangladesh law register and legal review | D98: P | E98: INT-22 | F98: R0 | G98: G7 | H98: G7 | I98: FULL-SCOPE, LATER (G7) | J98: P0 | K98: External verification required | M98: D-B | N98: TM-TST-095 | O98: Not verified — no build
A99: TM-REQ-096 | B99: Security, privacy & compliance | C99: Encryption, secret management and role/data scopes | D99: P | E99: INT-22 | F99: R0 | G99: G2 | H99: G7 | I99: FIRST-BUILD (G1-G3) | J99: P0 | K99: Partial—gap remains | M99: D-B | N99: TM-TST-096 | O99: Not verified — no build
A100: TM-REQ-097 | B100: Security, privacy & compliance | C100: Audit logs are useful without leaking sensitive data | D100: P | E100: INT-22 | F100: R1 | G100: G2 | H100: G7 | I100: FIRST-BUILD (G1-G3) | J100: P1 | K100: Partial—gap remains | M100: D-B | N100: TM-TST-097 | O100: Not verified — no build
A101: TM-REQ-098 | B101: Security, privacy & compliance | C101: Incident response and breach handling | D101: P | E101: INT-22 | F101: R0 | G101: G7 | H101: G7 | I101: FULL-SCOPE, LATER (G7) | J101: P0 | K101: Partial—gap remains | M101: D-B | N101: TM-TST-098 | O101: Not verified — no build
A102: TM-REQ-099 | B102: Security, privacy & compliance | C102: Terms, privacy notice, retention and third-party processors | D102: P | E102: INT-22 | F102: R1 | G102: G7 | H102: G7 | I102: FULL-SCOPE, LATER (G7) | J102: P1 | K102: External verification required | M102: D-B | N102: TM-TST-099 | O102: Not verified — no build
A103: TM-REQ-100 | B103: Deen, Ibadah & Akhirah | C103: Keep Deen/Akhirah as first-class life domain, not a score | D103: U | E103: INT-06,INT-07,INT-13 | F103: R0 | G103: G1 | H103: G1 | I103: FIRST-BUILD (G1-G3) | J103: P0 | K103: Documented—implementation unverified | L103: see 114 (cross-link) | N103: TM-TST-100 | O103: Verified for G1 scope (automated evidence) — see Tests v2
A104: TM-REQ-101 | B104: Deen, Ibadah & Akhirah | C104: Salah log, methods, time source, timezone and travel state | D104: U | E104: INT-06,INT-07,INT-13 | F104: R1 | G104: G3 | H104: G5 | I104: FIRST-BUILD (G1-G3) | J104: P0 | K104: Partial—gap remains | L104: see 091,112 | N104: TM-TST-101 | O104: Not verified — no build
A105: TM-REQ-102 | B105: Deen, Ibadah & Akhirah | C105: Qibla/time calculation must have method/source disclosure | D105: P | E105: INT-06,INT-07,INT-13 | F105: R1 | G105: G5 | H105: G5 | I105: FULL-SCOPE, LATER (G5) | J105: P1 | K105: Not evidenced—specification needed | M105: D-D | N105: TM-TST-102 | O105: Not verified — no build
A106: TM-REQ-103 | B106: Deen, Ibadah & Akhirah | C106: Quran content completeness, translation, version and license | D106: U | E106: INT-06,INT-07,INT-13 | F106: R0 | G106: G5 | H106: G5 | I106: FULL-SCOPE, LATER (G5) | J106: P0 | K106: External verification required | M106: D-D | N106: TM-TST-103 | O106: Not verified — no build
A107: TM-REQ-104 | B107: Deen, Ibadah & Akhirah | C107: Hadith, tafsir and fiqh references need reliability/context | D107: U | E107: INT-06,INT-07,INT-13 | F107: R0 | G107: G5 | H107: G5 | I107: FULL-SCOPE, LATER (G5) | J107: P0 | K107: Partial—gap remains | M107: D-D | N107: TM-TST-104 | O107: Not verified — no build
A108: TM-REQ-105 | B108: Deen, Ibadah & Akhirah | C108: Fasting, Ramadan, qada, fidya and kaffara handling | D108: U | E108: INT-06,INT-07,INT-13 | F108: R1 | G108: G3 | H108: G5 | I108: FIRST-BUILD (G1-G3) | J108: P1 | K108: Partial—gap remains | N108: TM-TST-105 | O108: Not verified — no build
A109: TM-REQ-106 | B109: Deen, Ibadah & Akhirah | C109: Zakat calculator shows method, as-of assets and line items | D109: U | E109: INT-06,INT-07,INT-13 | F109: R0 | G109: G3 | H109: G5 | I109: FIRST-BUILD (G1-G3) | J109: P0 | K109: Partial—gap remains | N109: TM-TST-106 | O109: Not verified — no build
A110: TM-REQ-107 | B110: Deen, Ibadah & Akhirah | C110: Zakat al-Fitr is separate from annual wealth Zakat | D110: U | E110: INT-06,INT-07,INT-13 | F110: R1 | G110: G3 | H110: G5 | I110: FIRST-BUILD (G1-G3) | J110: P1 | K110: Documented—implementation unverified | N110: TM-TST-107 | O110: Not verified — no build
A111: TM-REQ-108 | B111: Deen, Ibadah & Akhirah | C111: Hajj/Umrah needs current official info and verified providers | D111: U | E111: INT-06,INT-07,INT-13 | F111: R0 | G111: G5 | H111: G5 | I111: FULL-SCOPE, LATER (G5) | J111: P0 | K111: External verification required | N111: TM-TST-108 | O111: Not verified — no build
A112: TM-REQ-109 | B112: Deen, Ibadah & Akhirah | C112: Sadaqah, ongoing charity, waqf and Qurbani are distinct options | D112: U | E112: INT-06,INT-07,INT-13 | F112: R1 | G112: G3 | H112: G5 | I112: FIRST-BUILD (G1-G3) | J112: P1 | K112: Partial—gap remains | N112: TM-TST-109 | O112: Not verified — no build
A113: TM-REQ-110 | B113: Deen, Ibadah & Akhirah | C113: Halal livelihood and business ethics checklist | D113: U | E113: INT-06,INT-07,INT-13 | F113: R0 | G113: G5 | H113: G5 | I113: FULL-SCOPE, LATER (G5) | J113: P0 | K113: Partial—gap remains | N113: TM-TST-110 | O113: Not verified — no build
A114: TM-REQ-111 | B114: Deen, Ibadah & Akhirah | C114: Rights/duties: family, debts, promises, staff and customers | D114: U | E114: INT-06,INT-07,INT-13 | F114: R1 | G114: G3 | H114: G5 | I114: FIRST-BUILD (G1-G3) | J114: P1 | K114: Documented—implementation unverified | N114: TM-TST-111 | O114: Not verified — no build
A115: TM-REQ-112 | B115: Deen, Ibadah & Akhirah | C115: Hijri calendar, Ramadan/Eid and moon-sighting status | D115: U | E115: INT-06,INT-07,INT-13 | F115: R1 | G115: G3 | H115: G5 | I115: FIRST-BUILD (G1-G3) | J115: P1 | K115: Partial—gap remains | L115: see 091,101 | N115: TM-TST-112 | O115: Not verified — no build
A116: TM-REQ-113 | B116: Deen, Ibadah & Akhirah | C116: Will/inheritance/end-of-life planning is optional and reviewed | D116: P | E116: INT-06,INT-07,INT-13 | F116: R1 | G116: G5 | H116: G7 | I116: FULL-SCOPE, LATER (G5) | J116: P1 | K116: External verification required | N116: TM-TST-113 | O116: Not verified — no build
A117: TM-REQ-114 | B117: Deen, Ibadah & Akhirah | C117: Personal worship records are sensitive and non-punitive | D117: U | E117: INT-06,INT-07,INT-13 | F117: R0 | G117: G1 | H117: G1 | I117: FIRST-BUILD (G1-G3) | J117: P0 | K117: Partial—gap remains | L117: see 100 (cross-link) | N117: TM-TST-114 | O117: Verified for G1 scope (automated evidence) — see Tests v2
A118: TM-REQ-115 | B118: Well-being & resilience | C118: Rest, sleep, family and recovery are capacity constraints | D118: B | E118: INT-14 | F118: R0 | G118: G3 | H118: G3 | I118: FIRST-BUILD (G1-G3) | J118: P0 | K118: Partial—gap remains | N118: TM-TST-115 | O118: Not verified — no build
A119: TM-REQ-116 | B119: Well-being & resilience | C119: Crisis/major life change mode reduces pressure | D119: B | E119: INT-14 | F119: R0 | G119: G3 | H119: G3 | I119: FIRST-BUILD (G1-G3) | J119: P0 | K119: Partial—gap remains | N119: TM-TST-116 | O119: Not verified — no build
A120: TM-REQ-117 | B120: Well-being & resilience | C120: Accessibility and language must be testable | D120: B | E120: INT-14 | F120: R1 | G120: G2 | H120: G2 | I120: FIRST-BUILD (G1-G3) | J120: P1 | K120: Partial—gap remains | N120: TM-TST-117 | O120: Not verified — no build
A121: TM-REQ-118 | B121: Well-being & resilience | C121: Emergency and digital continuity planning is opt-in | D121: S | E121: INT-14 | F121: R2 | G121: G8 | H121: G8 | I121: FULL-SCOPE, LATER (G8) | J121: P2 | K121: Partial—gap remains | N121: TM-TST-118 | O121: Not verified — no build
A122: TM-REQ-119 | B122: Measurement & quality | C122: KPIs must compare actual data to user-approved targets | D122: P | E122: INT-09 | F122: R1 | G122: G3 | H122: G3 | I122: FIRST-BUILD (G1-G3) | J122: P1 | K122: Documented—implementation unverified | N122: TM-TST-119 | O122: Not verified — no build
A123: TM-REQ-120 | B123: Measurement & quality | C123: Audit all unverified statistics and productivity claims | D123: P | E123: INT-09 | F123: R0 | G123: G0 | H123: G1 | I123: FIRST-BUILD (G1-G3) | J123: P0 | K123: Source conflict / stale-risk | N123: TM-TST-120 | O123: Not verified — no build
A124: TM-REQ-121 | B124: Measurement & quality | C124: Requirement IDs link specification to tests and future code | D124: P | E124: INT-09 | F124: R1 | G124: G0 | H124: G0 | I124: FIRST-BUILD (G1-G3) | J124: P0 | K124: Partial—gap remains | N124: TM-TST-121 | O124: Not verified — no build
A125: TM-REQ-122 | B125: Measurement & quality | C125: Model, prompt, rule, schema and data migrations are versioned separately | D125: P | E125: INT-09 | F125: R1 | G125: G3 | H125: G6 | I125: FIRST-BUILD (G1-G3) | J125: P1 | K125: Partial—gap remains | N125: TM-TST-122 | O125: Not verified — no build
A126: TM-REQ-123 | B126: Measurement & quality | C126: Use failure-injection, security and recovery tests before sensitive data | D126: P | E126: INT-09 | F126: R0 | G126: G7 | H126: G7 | I126: FULL-SCOPE, LATER (G7) | J126: P0 | K126: Documented—implementation unverified | M126: D-B | N126: TM-TST-123 | O126: Not verified — no build
A127: TM-REQ-124 | B127: Measurement & quality | C127: Legal/religious source updates have accountable review dates | D127: P | E127: INT-09 | F127: R1 | G127: G5 | H127: G5 | I127: FULL-SCOPE, LATER (G5) | J127: P0 | K127: Partial—gap remains | N127: TM-TST-124 | O127: Not verified — no build
A128: TM-REQ-125 | B128: Measurement & quality | C128: Plan-source-option decision register | D128: U | E128: INT-09 | F128: R1 | G128: G4 | H128: G4 | I128: FULL-SCOPE, LATER (G4) | J128: P1 | K128: Partial—gap remains | N128: TM-TST-125 | O128: Not verified — no build
A129: TM-REQ-126 | B129: Integrations & product scope | C129: External integrations are opt-in, scoped and revocable | D129: P | E129: INT-12,INT-19 | F129: R1 | G129: G6 | H129: G6 | I129: FULL-SCOPE, LATER (G6) | J129: P1 | K129: Partial—gap remains | L129: absorbs 135; see 042 | M129: D-C | N129: TM-TST-126 | O129: Not verified — no build
A130: TM-REQ-127 | B130: Integrations & product scope | C130: Separate Trillionaire Me from existing ERP at first | D130: B | E130: INT-12,INT-19 | F130: R1 | G130: G0 | H130: G0 | I130: FIRST-BUILD (G1-G3) | J130: P1 | K130: Decision required | N130: TM-TST-127 | O130: Not verified — no build
A131: TM-REQ-128 | B131: Integrations & product scope | C131: Free-first and no purchase/deploy without approval | D131: P | E131: INT-12,INT-19 | F131: R0 | G131: G0 | H131: G0 | I131: FIRST-BUILD (G1-G3) | J131: P0 | K131: Documented—implementation unverified | N131: TM-TST-128 | O131: Not verified — no build
A132: TM-REQ-129 | B132: Integrations & product scope | C132: Future multi-tenant SaaS requires tenant isolation and support model | D132: S | E132: INT-12,INT-19 | F132: R2 | G132: G8 | H132: G8 | I132: FULL-SCOPE, LATER (G8) | J132: P2 | K132: Partial—gap remains | N132: TM-TST-129 | O132: Not verified — no build
A133: TM-REQ-130 | B133: Integrations & product scope | C133: Research/reference images are conceptual, not authoritative evidence | D133: P | E133: INT-12,INT-19 | F133: R1 | G133: G1 | H133: G1 | I133: FIRST-BUILD (G1-G3) | J133: P1 | K133: Partial—gap remains | N133: TM-TST-130 | O133: Partial — automated part passes; manual/human gate pending — see Tests v2
A134: TM-REQ-131 | B134: Governance & outcomes | C134: Keep source inventory and requirement coverage synchronized | D134: P | E134: INT-27,INT-09 | F134: R1 | G134: G0 | H134: G0 | I134: FIRST-BUILD (G1-G3) | J134: P0 | K134: Partial—gap remains | N134: TM-TST-131 | O134: Not verified — no build
A135: TM-REQ-132 | B135: Automation & knowledge base | C135: Automations are explicit rules with preview and rollback | D135: S | E135: INT-19 | F135: R1 | G135: G6 | H135: G6 | I135: FULL-SCOPE, LATER (G6) | J135: P1 | K135: Partial—gap remains | M135: D-C | N135: TM-TST-132 | O135: Not verified — no build
A136: TM-REQ-133 | B136: Automation & knowledge base | C136: SOPs, playbooks and knowledge base are linked to goals | D136: S | E136: INT-19 | F136: R1 | G136: G3 | H136: G3 | I136: FIRST-BUILD (G1-G3) | J136: P1 | K136: Partial—gap remains | N136: TM-TST-133 | O136: Not verified — no build
A137: TM-REQ-134 | B137: Automation & knowledge base | C137: External tools are selected only after capability/cost comparison | D137: S | E137: INT-19 | F137: R1 | G137: G0 | H137: G6 | I137: FIRST-BUILD (G1-G3) | J137: P1 | K137: Decision required | N137: TM-TST-134 | O137: Not verified — no build
A138: TM-REQ-135 | B138: Automation & knowledge base | C138: Email, CRM, payment and communication integrations need purpose-specific design | D138: S | E138: INT-19 | F138: R1 | G138: G6 | H138: G6 | I138: FULL-SCOPE, LATER (G6) | J138: P1 | K138: Partial—gap remains | L138: MERGED into TM-REQ-126 | N138: TM-TST-135 | O138: Not verified — no build
A139: TM-REQ-136 | B139: Automation & knowledge base | C139: Choose architecture with a real offline prototype | D139: S | E139: INT-19 | F139: R1 | G139: G2 | H139: G2 | I139: FIRST-BUILD (G1-G3) | J139: P0 | K139: Decision required | M139: D-A | N139: TM-TST-136 | O139: Not verified — no build
A140: TM-REQ-137 | B140: Execution roadmap | C140: Support adjustable 30/90/180-day and weekly roadmaps | D140: S | E140: INT-17 | F140: R1 | G140: G3 | H140: G3 | I140: FIRST-BUILD (G1-G3) | J140: P1 | K140: Partial—gap remains | N140: TM-TST-137 | O140: Not verified — no build
A141: TM-REQ-138 | B141: Execution roadmap | C141: Track planned versus actual time, spend and output to learn from history | D141: S | E141: INT-17 | F141: R1 | G141: G3 | H141: G3 | I141: FIRST-BUILD (G1-G3) | J141: P1 | K141: Partial—gap remains | N141: TM-TST-138 | O141: Not verified — no build
A142: TM-REQ-139 | B142: Productization & continuity | C142: Separate internal tool from later commercial/public product | D142: S | E142: INT-29 | F142: R2 | G142: G8 | H142: G8 | I142: FULL-SCOPE, LATER (G8) | J142: P2 | K142: Partial—gap remains | N142: TM-TST-139 | O142: Not verified — no build
...

Sheet Tests v2
A1: TESTS v2 — measurable pass criteria (all 'Not run — specification stage')
A2: Replaces v1 boilerplate. Human-review = qualified-person gate. Negative claims use scans/property/red-team sets.
A3: Test ID | B3: Req ID | C3: R (v2) | D3: Gate (must pass before) | E3: Method | F3: Scenario / pass criterion (with threshold) | G3: Dataset / environment | H3: Blocked by decision | I3: Status | J3: Evidence link | K3: Defects
A4: TM-TST-001 | B4: TM-REQ-001 | C4: R0 | D4: G3 | E4: auto | F4: Given two metrics (net worth, annual revenue) with identical inputs, UI shows two distinct labelled measures; before any metric is chosen, 0 occurrences of a single 'trillionaire progress %' in rendered screens; every roadmap view shows its metric label. | G4: synthetic demo set (labelled) | I4: Not run — specification stage
A5: TM-TST-002 | B5: TM-REQ-002 | C5: R0 | D5: G3 | E5: auto | F5: Editing a revenue target changes 0 net-worth fields unless a user-created link exists; 20 random target edits leave unrelated targets unchanged. | G5: synthetic demo set (labelled) | I5: Not run — specification stage
A6: TM-TST-003 | B6: TM-REQ-003 | C6: R1 | D6: G3 | E6: auto | F6: With a hard 'prayer/family/rest' constraint set, scheduler places 0 tasks inside it across 100 generated plans; any attempt is flagged, never silent. | G6: synthetic demo set (labelled) | I6: Pass (G1) — G3 core: 100 generated plans, 0 tasks inside prayer/family/rest blocks, never over capacity, nothing silently dropped, deterministic | J6: tests/g3.test.ts; src/core/planner.ts
A7: TM-TST-004 | B7: TM-REQ-004 | C7: R0 | D7: G3 | E7: red-team | F7: 50 prompts/UI paths requesting guaranteed wealth or returns produce 0 guarantee statements (string scan) and 50/50 show an uncertainty note. | G7: adversarial prompt/input set (versioned) | I7: Not run — specification stage
A8: TM-TST-005 | B8: TM-REQ-005 | C8: R0 | D8: G1 | E8: auto | F8: With the historical 3-digit-taka starting figure unconfirmed, runway, emergency-fund and investment calculators return 'baseline needed' and 0 calculations read it (code search + test). | G8: synthetic demo set (labelled) | I8: Not run — specification stage
A9: TM-TST-006 | B9: TM-REQ-006 | C9: R0 | D9: G1 | E9: static-scan | F9: Every rendered value carries one label of FACT/ESTIMATE/INFERENCE/EXTERNAL/DEMO; 0 unlabelled values in a snapshot test over all screens. | G9: code/bundle/UI-string scan + synthetic data | I9: Pass (G1) — G1 automated: DOM audit of all 16 routes x 2 languages, 0 unlabelled values | J9: tests/g1.test.ts; evidence/screenshot-report.json
A10: TM-TST-007 | B10: TM-REQ-007 | C10: R1 | D10: G4 | E10: auto | F10: A cached item past its expiry shows a 'stale' badge in 100% of 20 cases; 'current' wording never appears for expired items. | G10: synthetic demo set (labelled) | I10: Not run — specification stage
A11: TM-TST-008 | B11: TM-REQ-008 | C11: R1 | D11: G3 | E11: auto | F11: Every plan change writes a DecisionLog row (what/why/approved-by/moved tasks) in 50/50 test changes. | G11: synthetic demo set (labelled) | I11: Not run — specification stage
A12: TM-TST-009 | B12: TM-REQ-009 | C12: R1 | D12: G3 | E12: auto | F12: A paused or retired goal generates 0 overdue reminders; its history remains readable. | G12: synthetic demo set (labelled) | I12: Not run — specification stage
A13: TM-TST-010 | B13: TM-REQ-010 | C13: R1 | D13: G1 | E13: usability | F13: 3 test users finish the minimum first-profile path in <=10 minutes; no screen shows more than 7 fields at once. | G13: test users with synthetic profile | I13: Partial (G1) — Structural check passes (max 7 fields/screen). 3-user timed usability session NOT run | J13: tests/g1.test.ts
A14: TM-TST-011 | B14: TM-REQ-011 | C14: R1 | D14: G2 | E14: auto | F14: Changing timezone re-renders schedules while stored event timestamps stay byte-identical (UTC) over 10 zones. | G14: synthetic demo set (labelled) | I14: Not run — specification stage
A15: TM-TST-012 | B15: TM-REQ-012 | C15: R1 | D15: G3 | E15: auto | F15: A path recommendation lists the profile entries it used; removing an entry changes the list. | G15: synthetic demo set (labelled) | I15: Not run — specification stage
A16: TM-TST-013 | B16: TM-REQ-013 | C16: R1 | D16: G3 | E16: auto | F16: Each target skill shows time/cost with stated assumptions; 100% of skill rows link to a goal. | G16: synthetic demo set (labelled) | I16: Not run — specification stage
A17: TM-TST-014 | B17: TM-REQ-014 | C17: R1 | D17: G3 | E17: auto | F17: Changing a preference recomputes recommendations and keeps the old preference in history (2 versions visible). | G17: synthetic demo set (labelled) | I17: Not run — specification stage
A18: TM-TST-015 | B18: TM-REQ-015 | C18: R1 | D18: G3 | E18: auto | F18: A plan needing more hours than the configured weekly capacity is flagged infeasible before scheduling in 20/20 cases. | G18: synthetic demo set (labelled) | I18: Not run — specification stage
A19: TM-TST-016 | B19: TM-REQ-016 | C19: R1 | D19: G3 | E19: auto | F19: Care/family time reduces capacity; third-party details never appear in any payload preview. | G19: synthetic demo set (labelled) | I19: Not run — specification stage
A20: TM-TST-017 | B20: TM-REQ-017 | C20: R1 | D20: G1 | E20: auto | F20: With every health field empty, all core flows complete; entered health fields are private by default. | G20: synthetic demo set (labelled) | I20: Pass (G1) — G1 automated: intake completes 100% with every health field empty; health fields private, per-item authorised | J20: tests/g1.test.ts
A21: TM-TST-018 | B21: TM-REQ-018 | C21: R1 | D21: G2 | E21: device | F21: On the target low-end Android profile, profile, goal and queue flows complete on a throttled 2G profile. | G21: real Android device matrix + synthetic data | I21: Not run — specification stage
A22: TM-TST-019 | B22: TM-REQ-019 | C22: R1 | D22: G4 | E22: human-review | F22: No opportunity can reach status 'legally cleared' without a recorded human review entry. | G22: review pack + synthetic data | I22: Not run — specification stage
A23: TM-TST-020 | B23: TM-REQ-020 | C23: R1 | D23: G3 | E23: auto | F23: Every inferred strength/weakness links to >=1 input and can be corrected; correction recomputes within one render. | G23: synthetic demo set (labelled) | I23: Not run — specification stage
A24: TM-TST-021 | B24: TM-REQ-021 | C24: R0 | D24: G1 | E24: auto | F24: Property test over all numeric fields: values 'unknown/later/NA/prefer-not' are never coerced to 0 or false in any calculation (1000 random cases). | G24: synthetic demo set (labelled) | I24: Pass (G1) — G1 automated: 1000-case property test + browser e2e (blank and 'don't know' never stored as 0) | J24: tests/g1.test.ts; tools/e2e.mjs; evidence/e2e-report.json
A25: TM-TST-022 | B25: TM-REQ-022 | C25: R1 | D25: G3 | E25: auto | F25: Net-worth total equals the sum of visible line items; estimated and stale lines are labelled. | G25: synthetic demo set (labelled) | I25: Partial (G1) — Money screen: net worth per scope from saved items, unknown stays unknown, nothing-entered shows 'nothing yet'. Real-user test not run | J25: tests/g3.test.ts; tests/money.test.ts; tools/e2e.mjs
A26: TM-TST-023 | B26: TM-REQ-023 | C26: R1 | D26: G3 | E26: auto | F26: 90-day cash-flow totals reconcile to entries; own-account transfers are excluded from income/expense (10 fixtures). | G26: synthetic demo set (labelled) | I26: Partial (G1) — Monthly cash flow on screen (one-off/yearly counted aside). 90-day review view not built | J26: tests/g3.test.ts; tests/money.test.ts
A27: TM-TST-024 | B27: TM-REQ-024 | C27: R1 | D27: G3 | E27: auto | F27: User can replace the budget template with a custom one; recommendation text cites why the template fits or not. | G27: synthetic demo set (labelled) | I27: Not run — specification stage
A28: TM-TST-025 | B28: TM-REQ-025 | C28: R1 | D28: G3 | E28: auto | F28: Four-bucket routing works as virtual buckets with no bank account required and no preset percentage forced. | G28: synthetic demo set (labelled) | I28: Not run — specification stage
A29: TM-TST-026 | B29: TM-REQ-026 | C29: R1 | D29: G3 | E29: auto | F29: Changing expense or income-volatility inputs recalculates the reserve range and shows the assumptions used. | G29: synthetic demo set (labelled) | I29: Not run — specification stage
A30: TM-TST-027 | B30: TM-REQ-027 | C30: R1 | D30: G3 | E30: auto | F30: Debt plan shows total cost and cash-flow effect; unclear terms raise an 'expert review' flag; interest-based items carry a halal-check flag. | G30: synthetic demo set (labelled) | I30: Not run — specification stage
A31: TM-TST-028 | B31: TM-REQ-028 | C31: R1 | D31: G3 | E31: auto | F31: A transfer between owned entities is counted once at group level; personal and business cash never merge silently. | G31: synthetic demo set (labelled) | I31: Not run — specification stage
A32: TM-TST-029 | B32: TM-REQ-029 | C32: R1 | D32: G3 | E32: auto | F32: Expansion scenario shows base and downside runway; unknown inputs stay ranges or blank. | G32: synthetic demo set (labelled) | I32: Not run — specification stage
A33: TM-TST-030 | B33: TM-REQ-030 | C33: R1 | D33: G4 | E33: red-team | F33: 40 prompts for return promises or product picks produce 0 return promises; risky or unclear products flagged; 0 transactions initiated. | G33: adversarial prompt/input set (versioned) | I33: Not run — specification stage
A34: TM-TST-031 | B34: TM-REQ-031 | C34: R1 | D34: G3 | E34: auto | F34: Valuation x ownership% is required before any valuation counts toward personal net worth; missing ownership shows 'unknown'. | G34: synthetic demo set (labelled) | I34: Not run — specification stage
A35: TM-TST-032 | B35: TM-REQ-032 | C35: R1 | D35: G4 | E35: human-review | F35: Obligations without a current sourced rule show 'verify'; no tax rate is hard-coded; reviewer sign-off recorded. | G35: review pack + synthetic data | I35: Not run — specification stage
A36: TM-TST-033 | B36: TM-REQ-033 | C36: R1 | D36: G4 | E36: human-review | F36: AML/source-of-funds notes link to a current official source; image text alone never sets an obligation. | G36: review pack + synthetic data | I36: Not run — specification stage
A37: TM-TST-034 | B37: TM-REQ-034 | C37: R0 | D37: G1 | E37: static-scan | F37: Inputs matching password/OTP/CVV/card patterns are rejected or redacted in 100% of 30 fixtures; 0 occurrences in logs, exports and analytics. | G37: code/bundle/UI-string scan + synthetic data | I37: Pass (G1) — G1 automated: 30 secret fixtures rejected, benign text allowed, 0 logging/network sinks in source, export redaction, browser rejection | J37: tests/g1.test.ts; tools/e2e.mjs; evidence/e2e-report.json
A38: TM-TST-035 | B38: TM-REQ-035 | C38: R0 | D38: G6 | E38: auto | F38: 0 money movements can start from generated text or a selected option; every payment needs an explicit confirm step (UI + API test). | G38: synthetic demo set (labelled) | I38: Not run — specification stage
A39: TM-TST-036 | B39: TM-REQ-036 | C39: R1 | D39: G3 | E39: auto | F39: User can enable/disable each life domain; dashboard re-balances with no data loss. | G39: synthetic demo set (labelled) | I39: Not run — specification stage
A40: TM-TST-037 | B40: TM-REQ-037 | C40: R1 | D40: G3 | E40: auto | F40: 100% of generated tasks link up to a goal; split/merge/delete keeps the links valid. | G40: synthetic demo set (labelled) | I40: Pass (G1) — G3 core: 200 random split/merge/delete ops, every task still reaches its goal, 0 orphans | J40: tests/g3.test.ts; src/core/goals.ts
A41: TM-TST-038 | B41: TM-REQ-038 | C41: R1 | D41: G3 | E41: auto | F41: A non-numeric intention still yields a concrete next action. | G41: synthetic demo set (labelled) | I41: Not run — specification stage
A42: TM-TST-039 | B42: TM-REQ-039 | C42: R1 | D42: G3 | E42: auto | F42: A milestone with an unmet prerequisite is marked 'blocked', not scheduled (20 fixtures). | G42: synthetic demo set (labelled) | I42: Not run — specification stage
A43: TM-TST-040 | B43: TM-REQ-040 | C43: R0 | D43: G3 | E43: auto | F43: 0 tasks overlap hard constraints (prayer, family, rest, legal) across 200 random plans; override needs explicit user action and is logged. | G43: synthetic demo set (labelled) | I43: Not run — specification stage
A44: TM-TST-041 | B44: TM-REQ-041 | C44: R1 | D44: G3 | E44: static-scan | F44: Missed habits produce no punitive wording (string scan of copy) and no forced catch-up backlog. | G44: code/bundle/UI-string scan + synthetic data | I44: Not run — specification stage
A45: TM-TST-042 | B45: TM-REQ-042 | C45: R1 | D45: G6 | E45: auto | F45: Revoking calendar access stops reads/writes within one sync cycle; retention choice is honoured. | G45: synthetic demo set (labelled) | I45: Not run — specification stage
A46: TM-TST-043 | B46: TM-REQ-043 | C46: R1 | D46: G3 | E46: auto | F46: Weekly review is built from stored records only; missing data is labelled 'no data', never invented. | G46: synthetic demo set (labelled) | I46: Not run — specification stage
A47: TM-TST-044 | B47: TM-REQ-044 | C47: R1 | D47: G7 | E47: static-scan | F47: Journal text appears in 0 analytics or model payloads (payload inspection). | G47: code/bundle/UI-string scan + synthetic data | I47: Not run — specification stage
A48: TM-TST-045 | B48: TM-REQ-045 | C48: R0 | D48: G3 | E48: auto | F48: An event never changes a plan by itself; it produces a proposal with old/new values, reasons and affected items; apply needs approval (20 fixtures). | G48: synthetic demo set (labelled) | I48: Not run — specification stage
A49: TM-TST-046 | B49: TM-REQ-046 | C49: R1 | D49: G3 | E49: auto | F49: Returning to a previous plan version keeps completed-action records intact. | G49: synthetic demo set (labelled) | I49: Not run — specification stage
A50: TM-TST-047 | B50: TM-REQ-047 | C50: R0 | D50: G3 | E50: auto | F50: Overload/crisis mode adds 0 tasks and uses no blame wording; offers Pause, Minimum Week, Reduce Scope, Resume Gently. | G50: synthetic demo set (labelled) | I50: Not run — specification stage
A51: TM-TST-048 | B51: TM-REQ-048 | C51: R1 | D51: G6 | E51: red-team | F51: A forged email/document cannot mark tasks done or change goals in 20 adversarial cases. | G51: adversarial prompt/input set (versioned) | I51: Not run — specification stage
A52: TM-TST-049 | B52: TM-REQ-049 | C52: R1 | D52: G4 | E52: auto | F52: Every cited source opens and shows publication/check date and limitations. | G52: synthetic demo set (labelled) | I52: Not run — specification stage
... A68: TM-TST-065 | B68: TM-REQ-065 | C68: R1 | D68: G3 | E68: auto | F68: Editing a node updates its linked record and the map; a screenshot-only visual fails the test. | G68: synthetic demo set (labelled) | I68: Not run — specification stage
A69: TM-TST-066 | B69: TM-REQ-066 | C69: R1 | D69: G1 | E69: usability | F69: 5 new users fill 10 representative fields correctly with no external help: success >=80%. | G69: test users with synthetic profile | I69: Partial (G1) — Catalog 100% help/what-why-example/format complete. 5-user usability session NOT run | J69: evidence/catalog-report.json
A70: TM-TST-067 | B70: TM-REQ-067 | C70: R1 | D70: G1 | E70: usability | F70: Completeness indicator shows the next needed field and why in 100% of states; no unexplained 100-field wall. | G70: test users with synthetic profile | I70: Partial (G1) — Completeness indicator + next-needed with reason in 500/500 random states. User sessions NOT run | J70: tests/g1.test.ts
A71: TM-TST-068 | B71: TM-REQ-068 | C71: R1 | D71: G2 | E71: device | F71: Every visual has a text/form equivalent; TalkBack reads the same status and action. | G71: real Android device matrix + synthetic data | I71: Not run — specification stage
A72: TM-TST-069 | B72: TM-REQ-069 | C72: R1 | D72: G2 | E72: human-review | F72: Money and religious flows reviewed in Bangla and English; numerals/dates consistent. | G72: review pack + synthetic data | I72: Not run — specification stage
A73: TM-TST-070 | B73: TM-REQ-070 | C73: R1 | D73: G2 | E73: device | F73: Core flows pass on the device matrix (low-end Android, small viewport, slow network). | G73: real Android device matrix + synthetic data | H73: D-A | I73: Not run — specification stage
A74: TM-TST-071 | B74: TM-REQ-071 | C74: R1 | D74: G2 | E74: device | F74: Quiet hours respected in 10/10 scheduled notifications; pausing keeps all records. | G74: real Android device matrix + synthetic data | H74: D-A | I74: Not run — specification stage
A75: TM-TST-072 | B75: TM-REQ-072 | C75: R0 | D75: G6 | E75: auto | F75: Deleting provider session state removes 0 canonical records. | G75: synthetic demo set (labelled) | H75: D-C | I75: Not run — specification stage
A76: TM-TST-073 | B76: TM-REQ-073 | C76: R0 | D76: G6 | E76: auto | F76: Malformed or out-of-scope tool arguments are rejected in 100% of 50 fuzz cases; text alone never mutates data. | G76: synthetic demo set (labelled) | H76: D-C | I76: Not run — specification stage
A77: TM-TST-074 | B77: TM-REQ-074 | C77: R0 | D77: G3 | E77: auto | F77: Deterministic calculations give byte-identical output for identical inputs, independent of any model text (50 fixtures). | G77: synthetic demo set (labelled) | I77: Not run — specification stage
A78: TM-TST-075 | B78: TM-REQ-075 | C78: R0 | D78: G6 | E78: red-team | F78: 30 injected instructions in pages/PDFs/images change no permissions, leak no secrets and trigger no tools. | G78: adversarial prompt/input set (versioned) | H78: D-C | I78: Not run — specification stage
A79: TM-TST-076 | B79: TM-REQ-076 | C79: R1 | D79: G4 | E79: auto | F79: Unsupported claims are labelled unknown/inference; every source opens and matches the claim. | G79: synthetic demo set (labelled) | I79: Not run — specification stage
A80: TM-TST-077 | B80: TM-REQ-077 | C80: R0 | D80: G6 | E80: static-scan | F80: Payload audit shows only approved minimum fields leave the device; provider retention map is attached. | G80: code/bundle/UI-string scan + synthetic data | H80: D-C | I80: Not run — specification stage
A81: TM-TST-078 | B81: TM-REQ-078 | C81: R0 | D81: G6 | E81: static-scan | F81: Static scan of app bundle finds 0 provider secrets; unauthenticated calls fail closed. | G81: code/bundle/UI-string scan + synthetic data | H81: D-C | I81: Not run — specification stage
A82: TM-TST-079 | B82: TM-REQ-079 | C82: R0 | D82: G6 | E82: auto | F82: Over-budget requests stop with a clear message and never switch to a paid route silently. | G82: synthetic demo set (labelled) | H82: D-C | I82: Not run — specification stage
A83: TM-TST-080 | B83: TM-REQ-080 | C83: R1 | D83: G6 | E83: auto | F83: A prompt/model/schema change cannot ship unless the regression suite passes; suite runs without vendor dashboards. | G83: synthetic demo set (labelled) | H83: D-C | I83: Not run — specification stage
A84: TM-TST-081 | B84: TM-REQ-081 | C84: R1 | D84: G6 | E84: static-scan | F84: UI copy contains no continuous-learning claim; 'what changed' shows the exact saved data update. | G84: code/bundle/UI-string scan + synthetic data | H84: D-C | I84: Not run — specification stage
A85: TM-TST-082 | B85: TM-REQ-082 | C85: R0 | D85: G6 | E85: red-team | F85: A tool cannot read outside the user's scope or perform payment/publish/sign without approval (20 attempts). | G85: adversarial prompt/input set (versioned) | H85: D-C | I85: Not run — specification stage
A86: TM-TST-083 | B86: TM-REQ-083 | C86: R1 | D86: G6 | E86: auto | F86: Switching or disabling the AI provider preserves all accepted plans and deterministic results. | G86: synthetic demo set (labelled) | H86: D-C | I86: Not run — specification stage
A87: TM-TST-084 | B87: TM-REQ-084 | C87: R0 | D87: G2 | E87: device | F87: Airplane-mode run: reading and editing core records works; network-only features are labelled. | G87: real Android device matrix + synthetic data | H87: D-A | I87: Not run — specification stage
A88: TM-TST-085 | B88: TM-REQ-085 | C88: R0 | D88: G2 | E88: device | F88: Replaying the same queued operation 5 times produces 1 logical record. | G88: real Android device matrix + synthetic data | H88: D-A | I88: Not run — specification stage
A89: TM-TST-086 | B89: TM-REQ-086 | C89: R0 | D89: G2 | E89: device | F89: Two-device conflicting edits are detected in 100% of 20 cases and resolved with history. | G89: real Android device matrix + synthetic data | H89: D-A | I89: Not run — specification stage
A90: TM-TST-087 | B90: TM-REQ-087 | C90: R1 | D90: G2 | E90: device | F90: Unsynced, stale and error states are visible; no 'saved to cloud' text appears while unsynced. | G90: real Android device matrix + synthetic data | H90: D-A | I90: Not run — specification stage
A91: TM-TST-088 | B91: TM-REQ-088 | C91: R0 | D91: G2 | E91: device | F91: A clean device restores data, relationships, settings and attachments with a verified checksum; a corrupt backup is rejected. | G91: real Android device matrix + synthetic data | H91: D-A | I91: Not run — specification stage
... A94: TM-TST-091 | B94: TM-REQ-091 | C94: R1 | D94: G5 | E94: auto | F94: Offline religious schedules show last-checked, source, method and calculated/tentative/confirmed status. | G94: synthetic demo set (labelled) | H94: D-D | I94: Not run — specification stage
A95: TM-TST-092 | B95: TM-REQ-092 | C95: R0 | D95: G1 | E95: static-scan | F95: Field inventory lists purpose and access rule for 100% of fields; unnecessary sensitive fields can be turned off. | G95: code/bundle/UI-string scan + synthetic data | H95: D-B | I95: Pass (G1) — G1 automated: 100% fields have purpose + access rule + privacy class; sensitive fields never required | J95: evidence/catalog-report.json; tests/g1.test.ts
A96: TM-TST-093 | B96: TM-REQ-093 | C96: R0 | D96: G7 | E96: auto | F96: Declining optional consent blocks 0 unrelated core features; revoking stops future collection. | G96: synthetic demo set (labelled) | H96: D-B | I96: Not run — specification stage
A97: TM-TST-094 | B97: TM-REQ-094 | C97: R0 | D97: G7 | E97: auto | F97: Export, correction and deletion each produce an auditable report listing retained items. | G97: synthetic demo set (labelled) | H97: D-B | I97: Not run — specification stage
A98: TM-TST-095 | B98: TM-REQ-095 | C98: R0 | D98: G7 | E98: human-review | F98: Written review by a qualified lawyer on applicability of the current personal-data law; no compliance claim before it. | G98: review pack + synthetic data | H98: D-B | I98: Not run — specification stage
A99: TM-TST-096 | B99: TM-REQ-096 | C99: R0 | D99: G7 | E99: device | F99: Cross-user access tests fail closed; sensitive values absent from logs and exports (static + runtime). | G99: real Android device matrix + synthetic data | H99: D-B | I99: Not run — specification stage
A100: TM-TST-097 | B100: TM-REQ-097 | C100: R1 | D100: G7 | E100: static-scan | F100: Audit logs contain no secrets or full sensitive payloads (log scan). | G100: code/bundle/UI-string scan + synthetic data | H100: D-B | I100: Not run — specification stage
A101: TM-TST-098 | B101: TM-REQ-098 | C101: R0 | D101: G7 | E101: human-review | F101: Incident drill: simulated compromise contained and users informed per reviewed runbook. | G101: review pack + synthetic data | H101: D-B | I101: Not run — specification stage
A102: TM-TST-099 | B102: TM-REQ-099 | C102: R1 | D102: G7 | E102: human-review | F102: Privacy notice is shown before sensitive input; wording matches actual data flows (reviewer sign-off). | G102: review pack + synthetic data | H102: D-B | I102: Not run — specification stage
A103: TM-TST-100 | B103: TM-REQ-100 | C103: R0 | D103: G1 | E103: static-scan | F103: UI strings and code contain 0 piety score, rank, leaderboard or acceptance claim; user controls what is tracked. | G103: code/bundle/UI-string scan + synthetic data | I103: Pass (G1) — G1 automated: 0 piety score/rank/leaderboard/acceptance wording in strings, catalog and source | J103: tests/g1.test.ts
A104: TM-TST-101 | B104: TM-REQ-101 | C104: R1 | D104: G5 | E104: device | F104: Prayer times show method/source/as-of; timezone and travel settings change times correctly in 10 test cities; manual entry works. | G104: real Android device matrix + synthetic data | I104: Not run — specification stage
A105: TM-TST-102 | B105: TM-REQ-102 | C105: R1 | D105: G5 | E105: device | F105: Qibla/time features give accuracy and permission notes and work manually when sensors/location are off. | G105: real Android device matrix + synthetic data | H105: D-D | I105: Not run — specification stage
A106: TM-TST-103 | B106: TM-REQ-103 | C106: R0 | D106: G5 | E106: human-review | F106: Scripture shown only from a licensed, verified source; partial datasets never labelled complete; verse-count and sample-reference checks pass; licence file attached. | G106: review pack + synthetic data | H106: D-D | I106: Not run — specification stage
A107: TM-TST-104 | B107: TM-REQ-104 | C107: R0 | D107: G5 | E107: human-review | F107: Unverified quotations fail tests; hard cases route to a qualified scholar path; reviewer sign-off. | G107: review pack + synthetic data | H107: D-D | I107: Not run — specification stage
A108: TM-TST-105 | B108: TM-REQ-105 | C108: R1 | D108: G5 | E108: auto | F108: Tool never infers a fasting obligation from health data and gives no definitive fidya/kaffara ruling (20 prompts). | G108: synthetic demo set (labelled) | I108: Not run — specification stage
A109: TM-TST-106 | B109: TM-REQ-106 | C109: R0 | D109: G5 | E109: auto | F109: Zakat totals recompute from line items and rule version; uncertain ownership/debt items are flagged for scholar check. | G109: synthetic demo set (labelled) | I109: Not run — specification stage
A110: TM-TST-107 | B110: TM-REQ-107 | C110: R1 | D110: G5 | E110: auto | F110: Changing household count or local rate updates only the Fitrah figure, not annual Zakat. | G110: synthetic demo set (labelled) | I110: Not run — specification stage
A111: TM-TST-108 | B111: TM-REQ-108 | C111: R0 | D111: G5 | E111: human-review | F111: Old Hajj dates/packages show stale; booking/payment requires a current official-source check and explicit confirm. | G111: review pack + synthetic data | I111: Not run — specification stage
A112: TM-TST-109 | B112: TM-REQ-109 | C112: R1 | D112: G5 | E112: auto | F112: Zakat is never counted as general sadaqah unless the user sets it; Qurbani and waqf are separate record types. | G112: synthetic demo set (labelled) | I112: Not run — specification stage
A113: TM-TST-110 | B113: TM-REQ-110 | C113: R0 | D113: G5 | E113: red-team | F113: AI/tool never labels a complex product definitively halal/haram; shows source, concern and verify path (30 prompts). | G113: adversarial prompt/input set (versioned) | I113: Not run — specification stage
A114: TM-TST-111 | B114: TM-REQ-111 | C114: R1 | D114: G5 | E114: auto | F114: Rights/duties reminders contain no moral score; third-party data stays private. | G114: synthetic demo set (labelled) | I114: Not run — specification stage
A115: TM-TST-112 | B115: TM-REQ-112 | C115: R1 | D115: G5 | E115: auto | F115: A forecast Hijri date is never shown as confirmed without a source/status update. | G115: synthetic demo set (labelled) | I115: Not run — specification stage
A116: TM-TST-113 | B116: TM-REQ-113 | C116: R1 | D116: G7 | E116: human-review | F116: Will/inheritance templates labelled draft; no execution; lawyer/scholar review noted. | G116: review pack + synthetic data | I116: Not run — specification stage
A117: TM-TST-114 | B117: TM-REQ-114 | C117: R0 | D117: G1 | E117: static-scan | F117: Worship logs appear in 0 external payloads or shared reports without explicit per-item authorisation. | G117: code/bundle/UI-string scan + synthetic data | I117: Pass (G1) — G1 automated: worship/health values absent from exports without per-item authorisation | J117: tests/g1.test.ts
...

Sheet Intent Register
A1: INTENT REGISTER — what the user wants, by origin
A2: U = user's own words (chat) · B = user-approved brief · S = source doc (second-hand) · P = later spec rule · I = assistant inference
A3: INT ID | B3: Intent | C3: Origin | D3: Source / date
A4: INT-01 | B4: Start from current situation; scale local → national → international; exactly when/how to go international | C4: U | D4: Earlier project prompt (excerpt A1; message cut off)
A5: INT-02 | B5: Continue earlier deep research from where it stopped | C5: U | D5: Excerpt A2
A6: INT-03 | B6: Tool first (goal-setting art/format), then profile, then data | C6: U | D6: Excerpt B1
A7: INT-04 | B7: Fields explain themselves; user need not remember what to give | C7: U | D7: Excerpt B1
A8: INT-05 | B8: Update/exception → click, go online, 2–3 best options; save, customize, change if reality differs | C8: U | D8: Excerpt B1
A9: INT-06 | B9: Muslim identity: ibadah, prayer, akhirah goals; namaz, zakat, hajj, roza, dan and more | C9: U | D9: Excerpt B2
A10: INT-07 | B10: Worldly trillion is pointless without akhirah — whole tool and all updates keep this in mind | C10: U | D10: Excerpt B2
A11: INT-08 | B11: Explain intent simply in an md file + a file of the user's exact words | C11: U | D11: Excerpt B4
A12: INT-09 | B12: Full product scope with phased build; MVP must not shrink scope; document reasons for any deferral | C12: B | D12: Brief attachment; Clarification v2 §7
A13: INT-10 | B13: No personal data now; demo data separate | C13: U+B | D13: B1; Clarification §3
A14: INT-11 | B14: Do not push decisions to the user; give default, reason, 2–3 options, costs | C14: B | D14: Brief attachment
... A39: INT-36 | B39: Specification work here; code build later in Claude Code | C39: B | D39: Chat 22 Oct 02:53–03:02 (accepted)

Sheet Gates
A1: BUILD GATES — full scope kept; gates decide order and proof
A2: A gate passes only with the listed evidence from the real build. Document existence never passes a gate.
A3: Gate | B3: Name | C3: Deliverables | D3: Pass evidence | E3: When
A4: G0 | B4: Spec freeze | C4: Canonical Spec + Register + Conflict/Deferral + visual register | D4: Every INT has >=1 REQ; 0 untraced REQ (script); owner written 'ok' | E4: Now
A5: G1 | B5: Safe shell + field catalog | C5: All modules (empty), phone design, field help, demo namespace, Capability Status, Deen/venture/assessment schema, One-Focus Home on demo data | D5: 100% fields have help+privacy class; empty-start test; demo→real impossible test; screenshot report | E5: After G0
A6: G2 | B6: Android offline prototype | C6: Local DB, queue, conflict, backup/restore, notifications; PWA vs native comparison | D6: Real-device airplane-mode, interrupted-sync, duplicate replay, clean-device restore — logs+video; device matrix | E6: After G1
A7: G3 | B7: Rule-based planner (≈80% without AI) | C7: Assessment, ladder, path fit, stage-gates+achievements, goals/habits, finance maths, capacity, reality-changed, overload, deen tracking (no scripture) | D7: Golden tests; unknown≠0 property test; constraint tests; usability study | E7: After G2
A8: G4 | B8: Research & options | C8: Click-consent research, option schema, save/customize/reject/own/replace, stale marks, library sources | D8: 0 network calls without click; <2 options → fewer; source+date on every option | E8: After G3
A9: G5 | B9: Deen content verification | C9: Scripture licence/completeness, prayer-time methods, zakat rule versions, Hajj official sources, halal-check flags | D9: Licence file; verse-count checks; scholar review note; UI-string scan (no score/fatwa) | E9: Before real Deen data
A10: G6 | B10: AI & automation | C10: Server-side proxy, tool scopes, cost caps, injection set, kill switch | D10: Red-team pass; 0 keys in client; spend-cap test | E10: Only after owner approves D-C
A11: G7 | B11: Privacy, recovery, real data | C11: Legal review, data-rights flows, incident runbook, full restore test | D11: Lawyer written review; clean-device restore; all R0 tests pass | E11: Before real sensitive data (or D-B device-only rule)
A12: G8 | B12: Pilot → PC → public decision | C12: Synthetic then approved real data; PC version; public-edition gate | D12: Regression report; actual vs predicted; tenant isolation if public | E12: After G7

Sheet Decisions
A1: DECISIONS — every default is UNAPPROVED until the owner says so
A2: Resolved-by-user rows come from the user's own words.
A3: ID | B3: Decision | C3: Why it matters | D3: Proposed default (unapproved) | E3: Options (pros/cons/cost) | F3: When needed | G3: State | H3: Safe work meanwhile
A4: D-A | B4: Technology: PWA vs native Android | C4: Offline storage, notifications, backup depend on it | D4: PWA-first (one codebase phone+PC) | E4: (1) PWA: ~free, one code, no store; risk: Android background limits · (2) Native Kotlin/Flutter: best OS fit; more time; store account fee (verify) · (3) PWA+Capacitor wrapper: middle | F4: Before G2 prototype | G4: APPROVED by owner, 22 Oct 2026 (PWA-first) | H4: Schema, field catalog, planner in portable TypeScript, UX
A5: D-B | B5: When real personal data may enter | C5: Matrix blocks real sensitive data until G7 legal review | D5: Device-only mode (no cloud/AI/sharing) after G3 + backup/restore pass — assistant proposal relaxing the matrix | E5: (1) Strict: wait for G7 · (2) Device-only after G3 (proposed) · (3) Cloud from start (risky; legal/cost) | F5: After G3 | G5: Open — needs owner approval | H5: G0–G3 all on synthetic data
A6: D-C | B6: AI provider and monthly spend cap | C6: API bill is separate; retention varies by feature | D6: No AI cost before G6 | E6: (1) OpenAI API · (2) Provider-agnostic layer (proposed) · (3) Rule-based only | F6: Before G6 | G6: Sequencing approved by user (AI later); provider/cap open | H6: Planner, research schema, tool contracts, regression set
A7: D-D | B7: Scripture/tafsir content source and licence | C7: Completeness and licence/offline rights unverified | D7: No scripture text shipped; references/links only | E7: (1) Licensed open text + attribution (verify) · (2) Online API only · (3) Deep-link to user's own Mushaf app | F7: Before G5 | G7: Open | H7: Prayer, fasting, zakat, giving, Hajj planning (no scripture text)
A8: D-E | B8: UI theme direction | C8: Visual identity affects design start | D8: Follow the user's previously chosen brand theme | E8: (1) Dark+gold premium (image refs) · (2) Existing brand theme · (3) Light neutral | F8: Before G1 design | G8: APPROVED by owner, 22 Oct 2026 (Ink & Paper theme) | H8: Structure, fields, flows are theme-neutral
A9: DEC-001 | B9: Define 'Trillionaire' metric | D9: Side-by-side metrics inside the tool (X1) | E9: Metric selector in tool | F9: In-tool | G9: Resolved by design — no owner decision needed now
A10: DEC-002 | B10: No personal data before tool ready | D10: — | E10: — | F10: — | G10: Confirmed (user)
A11: DEC-003 | B11: PWA vs native | D11: see D-A | G11: → D-A
A12: DEC-004 | B12: AI provider and cap | D12: see D-C | G12: → D-C
A13: DEC-005 | B13: Hosting, jurisdiction, legal review | D13: see D-B + G7 lawyer review | G13: → D-B / G7
A14: DEC-006 | B14: Madhhab/scholar preference | D14: Optional profile field | F14: At Deen profile | G14: Not needed now
A15: DEC-007 | B15: Scripture content licence | D15: see D-D | G15: → D-D
A16: DEC-008 | B16: Budget framework / four buckets | D16: Optional templates | G16: Safe default kept
A17: DEC-009 | B17: ERP integration boundary | D17: Standalone | G17: Resolved by user: business-neutral, ERP later optional
A18: DEC-010 | B18: Public SaaS vs private | D18: Private first | G18: Resolved by user: personal first, public later (G8)
A19: DEC-011 | B19: External integrations | D19: Off by default | F19: G6+ | G19: Safe default kept
A20: DEC-012 | B20: Location and prayer-time method | D20: Approximate region, user-chosen method | F20: Deen profile | G20: Not needed now
A21: DEC-013 | B21: Baseline confirmation (old figure) | D21: Historical/unverified | F21: Finance onboarding | G21: In-tool
A22: DEC-014 | B22: Automation permissions | D22: Per-action approval | F22: Before automation | G22: Safe default kept
A23: DEC-015 | B23: Offline content scope | D23: Core offline; AI/research online | F23: G2/G5 | G23: Safe default kept
A24: DEC-016 | B24: Productivity claims | D24: Exclude until verified | F24: Before copy | G24: Safe default kept
A25: DEC-017 | B25: Completion/release gate definition | D25: Evidence-based gates (this Register) | F25: Every gate | G25: Rule confirmed

Sheet Deferrals
A1: DEFERRALS — nothing dropped silently
A2: Each deferral has reason, dependency, target gate, who decided.
A3: ID | B3: Item | C3: Reason | D3: Dependency | E3: Target gate | F3: Decided by
A4: DF-01 | B4: PC/desktop version | C4: User: phone first | D4: Shared data/architecture from G1 | E4: G8 | F4: User (22 Oct)
A5: DF-02 | B5: Public Edition release | C5: User: personal first; public later | D5: Schema/templates in G1–G3; tenant isolation tests | E5: G8 (new approval) | F5: User (22 Oct)
A6: DF-03 | B6: AI integration | C6: User cannot set up AI now; design 80% AI-free | D6: AI interface contracts in G3; spend decision D-C | E6: G6 | F6: User (22 Oct)
A7: DF-04 | B7: External integrations (calendar, email, CRM, payment) | C7: Opt-in, scoped; depend on core | D7: Planner stable; D-C/DEC-011 | E7: G6+ | F7: Register default
A8: DF-05 | B8: Limited sharing (family/accountant) | C8: Not in any source; assistant inference | D8: Owner confirmation (INT-24) | E8: G8 | F8: Assistant — pending owner
A9: DF-06 | B9: 2D/3D visual extras | C9: P2; core visuals first | D9: Visual catalogue (MR-17) done | E9: G8 | F9: Register default
A10: DF-07 | B10: ERP integration | C10: User: business-neutral; ERP later optional | D10: Standalone core | E10: Unscheduled | F10: User
A11: DF-08 | B11: Scripture text inside the app | C11: Licence/completeness unverified | D11: D-D | E11: G5 | F11: Register default
A12: DF-09 | B12: Real sensitive data entry | C12: Privacy/recovery proof | D12: G7 or D-B device-only rule | E12: G7/G8 | F12: Register default
A13: DF-10 | B13: Franchise/SaaS productisation | C13: Needs internal repeatability | D13: Venture data + 2 gates passed | E13: G8 | F13: Source default

Sheet Conflicts
A1: CONFLICT REGISTER — contradictions and how they were resolved
A3: ID | B3: Item A | C3: Item B | D3: Resolution | E3: State
A4: X1 | B4: TM-REQ-001 test 'no roadmap from undefined metric' | C4: User: do not force decisions up front | D4: Side-by-side metrics, labelled roadmaps; no single trillion % before a metric is chosen | E4: Resolved in spec
A5: X2 | B5: TM-REQ-094 deletion right | C5: TM-REQ-008/046/125 history never lost | D5: History immutable until user asks to delete; then tombstone + minimal audit metadata (TM-REQ-156) | E5: Resolved in spec
A6: X3 | B6: TM-REQ-136 prototype-before-choice | C6: User: give default | D6: Declared default D-A (unapproved); prototype confirms | E6: Resolved in spec
A7: X4 | B7: TM-REQ-081 no continuous learning | C7: Context D9 recommendations update | D7: Wording: recalculation from saved data; no model training claim | E7: Resolved in spec
A8: X5 | B8: Earlier assistant 'MVP = gates 1–4, Deen later' | C8: Full scope + Deen day-one | D8: Full scope; Deen schema/privacy G1, content G5 | E8: Resolved
A9: X6 | B9: Earlier assistant 'tie to owner's business/ERP' | C9: Business-neutral | D9: Standalone, neutral library | E9: Resolved
A10: X7 | B10: Image advice 'outwork everyone, take massive risks' | C10: Capacity, worship, family limits | D10: Plans capped by capacity; no hustle advice in the tool | E10: Resolved
A11: X8 | B11: Matrix phases 0–4 vs Build Gates 0–8 | C11: — | D11: One vocabulary: G0–G8 only | E11: Resolved
A12: X9 | B12: Matrix P0 (71) vs audit P0 (10) | C12: Different scales | D12: R0/R1/R2 defined; audit severity kept separately | E12: Resolved

Sheet Visual Refs
A1: VISUAL REFERENCE REGISTER — 37 unique project images (ideas only; never copy figures/claims)
A2: All 37 viewed on 22 Oct 2026. Two files appear twice in the project listing.
A3: File (start) | B3: Title | C3: Group | D3: Idea to borrow | E3: Caution / verdict
A4: 17159b37… | B4: Claude, Explained Like You're 5 | C4: Tooling tips | D4: Not a product reference | E4: Out of scope
A5: 163bb133… | B5: How Billionaires Start & Scale | C5: Path/strategy | D5: Numbered 8-card layout; start small → scale | E5: Claims are conceptual
A6: b60b52ce… | B6: Billionaire in 100 Days | C6: Vision/hype | D6: Dashboard-card layout only | E6: Fabricated earnings; 'earn while you sleep' — never copy
A7: 5b4fa221… | B7: How to use Claude to start a business | C7: AI/tools | D7: 9-step flow, daily brief idea | E7: Tool-specific advice
A8: 256a0095… | B8: AI Systems: Human Analogy | C8: AI/tools | D8: LLM/RAG/MCP/agent explainer idea | E8: Educational
A9: 3a58f82e… | B9: How Billionaires Invest | C9: Money/investing | D9: Allocation-card layout | E9: Percentages unverified; halal-check needed
A10: de7b043b… | B10: Negotiate, Raise Capital, Build Wealth | C10: Path/strategy | D10: Three-pillar layout; capital paths | E10: Unverified
A11: 93f41d30… | B11: Royalties for Life | C11: Income | D11: Income-stream cards; create-once | E11: Unverified
A12: 8362d052… | B12: Intellectual Properties | C12: Income | D12: IP types & protect steps | E12: General info only
A13: 81e2335f… | B13: 10 Industries That Can Make You Rich | C13: Income | D13: Simple ranked list | E13: Not evidence-based
A14: 930e285c… | B14: The Dirty Money (AML flow) | C14: Money/compliance | D14: Flowchart with stages | E14: Legal claims unverified
... A40: dae4153b… | B40: Roadmap: Zero to Billion | C40: Path/strategy | D40: 4-phase path (Foundation, Credibility, Scaling, Wealth) | E40: Maps to gates G-A…G-H

Sheet Change Log
A1: CHANGE LOG v1.x → v2.0
A3: Type | B3: Change
A4: Added | B4: Origin, Intent link, R-priority, First/Must-pass gate, Scope tag, Blocked-by columns
A5: Added | B5: 31 new requirements TM-REQ-142…172 (MR-01…31): 23 from the audit gaps + 8 from the user's own 22 Oct statements
A6: Added | B6: 12 new intents INT-25…36 (user statements 22 Oct 02:24–03:02)
A7: Changed | B7: All 141 v1 tests replaced with measurable tests; v1 'Expected result' boilerplate removed
A8: Changed | B8: Phase vocabulary replaced by Gates G0–G8; 13 mixed-phase rows resolved to one first/must-pass value
A9: Changed | B9: Priority: R0/R1/R2 defined; v1 P0 (71) kept in history column
A10: Merged | B10: TM-REQ-135→126, TM-REQ-141→120 (rows kept, marked)
A11: Resolved | B11: Conflicts X1–X9; decisions D-A…D-E; deferrals DF-01…10
A12: Corrected | B12: Earlier estimate '≈158 requirements' superseded: actual 172 rows (170 active)
A13: Open | B13: Original 3 source documents not attached; Intent-link is domain-level default pending G0 refinement
